vtds_base/__init__.py
vtds_base/base_config.py
vtds_base/commands.py
vtds_base/config_operations.py
vtds_base/entrypoint.py
vtds_base/errors.py
vtds_base/logs.py
vtds_base/stack.py
vtds_base/template_operations.py
vtds_base/layers/__init__.py
vtds_base/layers/base_config.py
vtds_base/layers/layerapi.py
vtds_base/layers/application/__init__.py
vtds_base/layers/application/application.py
vtds_base/layers/cluster/__init__.py
vtds_base/layers/cluster/api_objects.py
vtds_base/layers/cluster/cluster.py
vtds_base/layers/platform/__init__.py
vtds_base/layers/platform/platform.py
vtds_base/layers/provider/__init__.py
vtds_base/layers/provider/api_objects.py
vtds_base/layers/provider/provider.py
vtds_base-0.0.39.dist-info/licenses/LICENSE
vtds_base-0.0.39.dist-info/METADATA
vtds_base-0.0.39.dist-info/WHEEL
vtds_base-0.0.39.dist-info/top_level.txt
vtds_base-0.0.39.dist-info/RECORD
